DI2/DI2.py
DI2/__init__.py
DI2-1.0.2.dist-info/LICENSE
DI2-1.0.2.dist-info/METADATA
DI2-1.0.2.dist-info/WHEEL
DI2-1.0.2.dist-info/top_level.txt
DI2-1.0.2.dist-info/RECORD
