Metadata-Version: 2.1
Name: DI2
Version: 1.0.2
Summary: An an unsupervised discretization method, DI2, for variables with arbitrarily skewed distributions.
Home-page: https://github.com/JupitersMight/DI2
Author: L. Alexandre, R.S. Costa, R. Henriques
Author-email: leonardoalexandre@tecnico.ulisboa.pt
License: UNKNOWN
Project-URL: Bug Tracker, https://github.com/JupitersMight/DI2/issues
Keywords: multi-item discretization,prior-free discretization,heterogeneous biological data,data mining
Platform: UNKNOWN
Classifier: Programming Language :: Python :: 3
Classifier: License :: OSI Approved :: MIT License
Classifier: Operating System :: OS Independent
Requires-Python: >=3.7
License-File: LICENSE
